verisynth/__init__.py
verisynth/cli.py
verisynth/lineage.py
verisynth/privacy.py
verisynth/schema.py
verisynth/synth.py
verisynth/verify.py
verisynth_core-0.1.0.dist-info/licenses/LICENSE
verisynth_core-0.1.0.dist-info/METADATA
verisynth_core-0.1.0.dist-info/WHEEL
verisynth_core-0.1.0.dist-info/entry_points.txt
verisynth_core-0.1.0.dist-info/top_level.txt
verisynth_core-0.1.0.dist-info/RECORD
