Metadata-Version: 2.4
Name: verisynth-core
Version: 0.1.0
Summary: Open-source synthetic data generator with cryptographic proof receipts.
Author-email: "VeriSynth.ai" <info@verisynth.ai>
License-Expression: MIT
Project-URL: Homepage, https://verisynth.ai
Project-URL: Repository, https://github.com/VeriSynthAI/verisynth-core
Project-URL: Issues, https://github.com/VeriSynthAI/verisynth-core/issues
Keywords: synthetic-data,privacy,gaussian-copula,ml,verifiable
Classifier: Programming Language :: Python :: 3
Classifier: Programming Language :: Python :: 3 :: Only
Classifier: Programming Language :: Python :: 3.9
Classifier: Programming Language :: Python :: 3.10
Classifier: Programming Language :: Python :: 3.11
Classifier: Programming Language :: Python :: 3.12
Classifier: Programming Language :: Python :: 3.13
Classifier: Intended Audience :: Science/Research
Classifier: Topic :: Scientific/Engineering :: Information Analysis
Requires-Python: >=3.9
License-File: LICENSE
Requires-Dist: pandas>=2.0
Requires-Dist: numpy>=1.24
Requires-Dist: sdv>=1.12.0
Requires-Dist: scipy>=1.10
Dynamic: license-file
